frappe_crm_mcp/__init__.py
frappe_crm_mcp/client.py
frappe_crm_mcp/server.py
frappe_crm_mcp/tools/__init__.py
frappe_crm_mcp/tools/activities.py
frappe_crm_mcp/tools/contacts.py
frappe_crm_mcp/tools/deals.py
frappe_crm_mcp/tools/leads.py
frappe_crm_mcp/tools/meta.py
frappe_crm_mcp/tools/notes.py
frappe_crm_mcp/tools/organizations.py
frappe_crm_mcp/tools/statuses.py
frappe_crm_mcp/tools/tasks.py
frappe_crm_mcp-0.0.6.dist-info/METADATA
frappe_crm_mcp-0.0.6.dist-info/WHEEL
frappe_crm_mcp-0.0.6.dist-info/entry_points.txt
frappe_crm_mcp-0.0.6.dist-info/licenses/LICENSE
frappe_crm_mcp-0.0.6.dist-info/RECORD
