Metadata-Version: 2.4
Name: frappe-crm-mcp
Version: 0.0.6
Summary: MCP server for Frappe CRM - interact with your CRM through AI assistants
Project-URL: Homepage, https://github.com/joehaddad2000/frappe-crm-mcp
Project-URL: Repository, https://github.com/joehaddad2000/frappe-crm-mcp
Project-URL: Issues, https://github.com/joehaddad2000/frappe-crm-mcp/issues
Author-email: Joe Haddad <joehaddad129@gmail.com>
License-Expression: MIT
License-File: LICENSE
Keywords: ai,claude,crm,frappe,llm,mcp
Classifier: Development Status :: 3 - Alpha
Classifier: Intended Audience :: Developers
Classifier: License :: OSI Approved :: MIT License
Classifier: Programming Language :: Python :: 3
Classifier: Programming Language :: Python :: 3.11
Classifier: Programming Language :: Python :: 3.12
Classifier: Programming Language :: Python :: 3.13
Requires-Python: >=3.11
Requires-Dist: fastmcp>=2.14.3
